<?xml version="1.0" encoding="UTF-8"?><?xml-stylesheet type='text/xsl' href='_UpgradeReport_Files/UpgradeReport.xslt'?><UpgradeLog>
<Properties><Property Name="Solution" Value="BT1">
</Property><Property Name="Solution File" Value="C:\Users\Administrator\Desktop\SOCKET\BT1\BT1.sln">
</Property><Property Name="User Options File" Value="C:\Users\Administrator\Desktop\SOCKET\BT1\BT1.suo">
</Property><Property Name="Date" Value="19 ThaÌng Ba 2013">
</Property><Property Name="Time" Value="21:53 CH">
</Property></Properties><Event ErrorLevel="0" Project="" Source="BT1.sln" Description="File successfully backed up as C:\Users\Administrator\Desktop\SOCKET\BT1\Backup\BT1.sln">
</Event><Event ErrorLevel="0" Project="" Source="BT1.suo" Description="File successfully backed up as C:\Users\Administrator\Desktop\SOCKET\BT1\Backup\BT1.suo">
</Event><Event ErrorLevel="0" Project="BT1" Source="BT1\BT1.csproj" Description="Project file successfully backed up as C:\Users\Administrator\Desktop\SOCKET\BT1\Backup\BT1\BT1.csproj">
</Event><Event ErrorLevel="0" Project="BT1" Source="BT1\Program.cs" Description="File successfully backed up as C:\Users\Administrator\Desktop\SOCKET\BT1\Backup\BT1\Program.cs">
</Event><Event ErrorLevel="0" Project="BT1" Source="BT1\Properties\AssemblyInfo.cs" Description="File successfully backed up as C:\Users\Administrator\Desktop\SOCKET\BT1\Backup\BT1\Properties\AssemblyInfo.cs">
</Event><Event ErrorLevel="0" Project="BT1" Source="BT1\BT1.csproj" Description="Project converted successfully">
</Event><Event ErrorLevel="3" Project="BT1" Source="BT1\BT1.csproj" Description="Converted">
</Event><Event ErrorLevel="0" Project="" Source="BT1.sln" Description="Solution converted successfully">
</Event><Event ErrorLevel="3" Project="" Source="BT1.sln" Description="Converted">
</Event><Event ErrorLevel="0" Project="BT1" Source="BT1\BT1.csproj" Description="Scan complete: Upgrade not required for project files.">
</Event></UpgradeLog>